mrseq/VERSION
mrseq/__init__.py
mrseq/_version.py
mrseq/preparations/__init__.py
mrseq/preparations/t1_inv_prep.py
mrseq/preparations/t1rho_prep.py
mrseq/preparations/t2_prep.py
mrseq/scripts/__init__.py
mrseq/scripts/radial_flash.py
mrseq/scripts/spiral_flash.py
mrseq/scripts/t1_inv_rec_gre_single_line.py
mrseq/scripts/t1_inv_rec_se_single_line.py
mrseq/scripts/t1_molli_bssfp.py
mrseq/scripts/t1_t2_spiral_cmrf.py
mrseq/scripts/t1rho_se_single_line.py
mrseq/scripts/t2_multi_echo_se_single_line.py
mrseq/scripts/t2star_multi_echo_flash.py
mrseq/utils/__init__.py
mrseq/utils/constants.py
mrseq/utils/ismrmrd.py
mrseq/utils/sequence_helper.py
mrseq/utils/system_defaults.py
mrseq/utils/trajectory.py
mrseq/utils/vds.py
mrseq-0.260119.dist-info/licenses/LICENSE
mrseq-0.260119.dist-info/METADATA
mrseq-0.260119.dist-info/WHEEL
mrseq-0.260119.dist-info/top_level.txt
mrseq-0.260119.dist-info/RECORD
