Metadata-Version: 2.4
Name: mrseq
Version: 0.260119
Summary: (Py)Pulseq-based MRI sequences.
Author-email: Patrick Schuenke <patrick.schuenke@ptb.de>, Christoph Kolbitsch <christoph.kolbitsch@ptb.de>
Project-URL: repository, https://github.com/PTB-MR/mrseq
Keywords: MRI, Pulseq, PyPulseq, pulse sequence
Classifier: License :: OSI Approved :: Apache Software License
Classifier: Programming Language :: Python
Classifier: Programming Language :: Python :: 3.10
Classifier: Programming Language :: Python :: 3.11
Classifier: Programming Language :: Python :: 3.12
Classifier: Programming Language :: Python :: 3.13
Classifier: Programming Language :: Python :: 3.14
Classifier: Programming Language :: Python :: 3 :: Only
Requires-Python: <3.15,>=3.10
License-File: LICENSE
Requires-Dist: numpy<3.0,>=1.23
Requires-Dist: matplotlib<4.0
Requires-Dist: pypulseq>=1.4.1
Requires-Dist: ismrmrd>=1.14.1
Provides-Extra: tests
Requires-Dist: coverage; extra == "tests"
Requires-Dist: codecov; extra == "tests"
Requires-Dist: pre-commit; extra == "tests"
Requires-Dist: pytest; extra == "tests"
Requires-Dist: pytest-cov; extra == "tests"
Requires-Dist: pytest-xdist; extra == "tests"
Provides-Extra: examples
Requires-Dist: mrzerocore>=0.4.3; extra == "examples"
Requires-Dist: mrpro; extra == "examples"
Requires-Dist: cmap; extra == "examples"
Requires-Dist: jupyter-book<2.0; extra == "examples"
Provides-Extra: dev
Requires-Dist: mrseq[examples,tests]; extra == "dev"
Dynamic: license-file
